LICENSE
MANIFEST.in
README
pyproject.toml
setup.py
dsdp/C/pyreadsdpa.c
dsdp/C/allc/allbounds.c
dsdp/C/allc/cholmat.c
dsdp/C/allc/cholmat2.c
dsdp/C/allc/dbounds.c
dsdp/C/allc/diag.c
dsdp/C/allc/dlpack.c
dsdp/C/allc/drowcol.c
dsdp/C/allc/dsdpadddata.c
dsdp/C/allc/dsdpadddatamat.c
dsdp/C/allc/dsdpblock.c
dsdp/C/allc/dsdpcg.c
dsdp/C/allc/dsdpcone.c
dsdp/C/allc/dsdpconverge.c
dsdp/C/allc/dsdpcops.c
dsdp/C/allc/dsdpdatamat.c
dsdp/C/allc/dsdpdsmat.c
dsdp/C/allc/dsdpdualmat.c
dsdp/C/allc/dsdperror.c
dsdp/C/allc/dsdplog.c
dsdp/C/allc/dsdploginfo.c
dsdp/C/allc/dsdplp.c
dsdp/C/allc/dsdpobjcone.c
dsdp/C/allc/dsdpprintout.c
dsdp/C/allc/dsdprescone.c
dsdp/C/allc/dsdpschurmat.c
dsdp/C/allc/dsdpschurmatadd.c
dsdp/C/allc/dsdpsetdata.c
dsdp/C/allc/dsdpsetoptions.c
dsdp/C/allc/dsdpsetup.c
dsdp/C/allc/dsdpstep.c
dsdp/C/allc/dsdptime.c
dsdp/C/allc/dsdpx.c
dsdp/C/allc/dsdpxmat.c
dsdp/C/allc/dtrsm2.c
dsdp/C/allc/dualalg.c
dsdp/C/allc/dualimpl.c
dsdp/C/allc/dufull.c
dsdp/C/allc/identity.c
dsdp/C/allc/onemat.c
dsdp/C/allc/printsdpa.c
dsdp/C/allc/rmmat.c
dsdp/C/allc/sdpalloc.c
dsdp/C/allc/sdpcompute.c
dsdp/C/allc/sdpcone.c
dsdp/C/allc/sdpconesetup.c
dsdp/C/allc/sdpconevec.c
dsdp/C/allc/sdpdvct.c
dsdp/C/allc/sdpexit.c
dsdp/C/allc/sdpkcone.c
dsdp/C/allc/sdpmatx.c
dsdp/C/allc/sdpnfac.c
dsdp/C/allc/sdporder.c
dsdp/C/allc/sdpsss.c
dsdp/C/allc/sdpsymb.c
dsdp/C/allc/sdpvec.c
dsdp/C/allc/sdpxlist.c
dsdp/C/allc/spds.c
dsdp/C/allc/vech.c
dsdp/C/allc/vechu.c
dsdp/C/allc/zeromat.c
dsdp/C/allinclude/dsdp.h
dsdp/C/allinclude/dsdp5.h
dsdp/C/allinclude/dsdpbasictypes.h
dsdp/C/allinclude/dsdpcg.h
dsdp/C/allinclude/dsdpcone.h
dsdp/C/allinclude/dsdpcone_impl.h
dsdp/C/allinclude/dsdpconverge.h
dsdp/C/allinclude/dsdpdatamat.h
dsdp/C/allinclude/dsdpdatamat_impl.h
dsdp/C/allinclude/dsdpdsmat.h
dsdp/C/allinclude/dsdpdsmat_impl.h
dsdp/C/allinclude/dsdpdualmat.h
dsdp/C/allinclude/dsdpdualmat_impl.h
dsdp/C/allinclude/dsdplanczos.h
dsdp/C/allinclude/dsdplapack.h
dsdp/C/allinclude/dsdpmem.h
jlc_scikit_dsdp.egg-info/PKG-INFO
jlc_scikit_dsdp.egg-info/SOURCES.txt
jlc_scikit_dsdp.egg-info/dependency_links.txt
jlc_scikit_dsdp.egg-info/requires.txt
jlc_scikit_dsdp.egg-info/top_level.txt