Metadata-Version: 2.4
Name: jlc-scikit-dsdp
Version: 0.3
Summary: Python interface to DSDP semidefinite programming library
Author-email: Zhisu Zhu <zhuzhisu@alumni.stanford.edu>, Yinyu Ye <yyye@stanford.edu>
License-Expression: GPL-3.0-or-later
Project-URL: Homepage, http://www.mcs.anl.gov/hs/software/DSDP/
Project-URL: Repository, https://github.com/zhisu/scikit-dsdp
Project-URL: Issues, https://github.com/zhisu/scikit-dsdp/issues
Requires-Python: >=3.6
License-File: LICENSE
Requires-Dist: numpy>=1.19.0
Requires-Dist: scikit_learn>=0.22
Requires-Dist: scipy>=1.5.2
Dynamic: license-file
